<?xml version="1.0" standalone="yes"?>
<LaneMapper>
  <Centers>
    <Name>G:\DotNet_dwd\2017\KegelLaneMapper\KegelLaneMapper\bin\Debug\Calibration\Converted\LM-2412.xml</Name>
    <Phone />
    <Email />
    <Address />
    <City />
    <State />
    <ZIP>2412</ZIP>
    <Country />
    <Notes />
    <FileType>0</FileType>
  </Centers>
  <Mappers>
    <ID>1</ID>
    <Lane>1</Lane>
    <Date>2018-08-15T07:36:33.1158151-04:00</Date>
    <Notes />
  </Mappers>
  <Readings>
    <Feet>0</Feet>
    <Inches>0</Inches>
    <Step>1</Step>
    <MapperID>1</MapperID>
    <Cross>0</Cross>
    <Length>0</Length>
    <D1>3791</D1>
    <D2>3815</D2>
    <D3>3816</D3>
    <D4>3818</D4>
    <D5>3811</D5>
    <D6>3809</D6>
    <D7>3809</D7>
    <D8>3813</D8>
    <D9>3815</D9>
    <D10>3811</D10>
    <D11>3811</D11>
    <D12>3804</D12>
    <D13>3800</D13>
    <D14>3799</D14>
    <D15>3801</D15>
    <D16>3804</D16>
    <D17>3802</D17>
    <D18>3801</D18>
    <D19>3794</D19>
    <D20>3791</D20>
    <D21>3789</D21>
    <D22>3794</D22>
    <D23>3796</D23>
    <D24>3797</D24>
    <D25>3789</D25>
    <D26>3779</D26>
    <D27>3769</D27>
    <D28>3763</D28>
    <D29>3765</D29>
    <D30>3766</D30>
    <D31>3760</D31>
    <D32>3757</D32>
    <D33>3751</D33>
    <D34>3742</D34>
    <D35>3737</D35>
    <D36>3739</D36>
    <D37>3742</D37>
    <D38>3741</D38>
    <D39>3740</D39>
    <D40>3732</D40>
    <D41>3725</D41>
    <D42>3724</D42>
    <D43>3727</D43>
    <D44>3727</D44>
    <D45>3727</D45>
    <D46>3727</D46>
    <D47>3721</D47>
    <D48>3715</D48>
    <D49>3717</D49>
    <D50>3720</D50>
    <D51>3720</D51>
    <D52>3716</D52>
    <D53>3708</D53>
    <D54>3697</D54>
    <D55>3692</D55>
    <D56>3690</D56>
    <D57>3690</D57>
    <D58>3690</D58>
    <D59>3687</D59>
    <D60>3676</D60>
    <D61>3661</D61>
    <D62>3657</D62>
    <D63>3656</D63>
    <D64>3662</D64>
    <D65>3667</D65>
    <D66>3666</D66>
    <D67>3658</D67>
    <D68>3648</D68>
    <D69>3637</D69>
    <D70>3631</D70>
    <D71>3632</D71>
    <D72>3631</D72>
    <D73>3630</D73>
    <D74>3623</D74>
    <D75>3611</D75>
    <D76>3612</D76>
    <D77>3613</D77>
  </Readings>
</LaneMapper>